coo_optimizer/__init__.py
coo_optimizer/coo.py
coo_optimizer-2.3.0.dist-info/licenses/LICENSE.txt
tests/__init__.py
tests/test_coo.py
coo_optimizer-2.3.0.dist-info/METADATA
coo_optimizer-2.3.0.dist-info/WHEEL
coo_optimizer-2.3.0.dist-info/top_level.txt
coo_optimizer-2.3.0.dist-info/RECORD
