Metadata-Version: 2.4
Name: coo_optimizer
Version: 2.3.0
Summary: Canine Olfactory Optimization Algorithm
Home-page: https://github.com/SandipGarai/coo_optimizer
Author: Sandip Garai
Author-email: Sandip Garai <sandipnicksandy@gmail.com>
License: MIT
Project-URL: Homepage, https://github.com/SandipGarai/coo_optimizer
Project-URL: Documentation, https://coo_optimizer.readthedocs.io
Project-URL: Repository, https://github.com/SandipGarai/coo_optimizer
Keywords: optimization,metaheuristic,machine-learning
Classifier: Development Status :: 4 - Beta
Classifier: Intended Audience :: Science/Research
Classifier: License :: OSI Approved :: MIT License
Classifier: Programming Language :: Python :: 3
Requires-Python: >=3.7
License-File: LICENSE.txt
Dynamic: author
Dynamic: home-page
Dynamic: license-file
Dynamic: requires-python
